[
    {
        "title": "Reignat",
        "summary": "Новость: Reignat. <p>\n            Privacy-friendly web analytics with realtime AI insights\n          </p>\n   ... (Установите API ключ в bot.py)...",
        "content": "Новость: Reignat. <p>\n            Privacy-friendly web analytics with realtime AI insights\n          </p>\n   ... (Установите API ключ в bot.py)",
        "link": "https://www.producthunt.com/products/reignat",
        "date": "2026-07-20"
    },
    {
        "title": "Spycost",
        "summary": "Новость: Spycost. <p>\n            Fell for a discount again?\n          </p>\n          <p>\n            <a href... (Установите API ключ в bot.py)...",
        "content": "Новость: Spycost. <p>\n            Fell for a discount again?\n          </p>\n          <p>\n            <a href... (Установите API ключ в bot.py)",
        "link": "https://www.producthunt.com/products/spycost",
        "date": "2026-07-20"
    },
    {
        "title": "‘Odyssey’ director Christopher Nolan calls AI an obvious ‘Trojan horse’",
        "summary": "Новость: ‘Odyssey’ director Christopher Nolan calls AI an obvious ‘Trojan horse’. \"Everybody knows the Greeks... (Установите API ключ в bot.py)...",
        "content": "Новость: ‘Odyssey’ director Christopher Nolan calls AI an obvious ‘Trojan horse’. \"Everybody knows the Greeks... (Установите API ключ в bot.py)",
        "link": "https://techcrunch.com/2026/07/19/odyssey-director-christopher-nolan-calls-ai-an-obvious-trojan-horse/",
        "date": "2026-07-19"
    },
    {
        "title": "OpenSEO",
        "summary": "Новость: OpenSEO. <p>\n            The open source Ahrefs alternative\n          </p>\n          <p>\n           ... (Установите API ключ в bot.py)...",
        "content": "Новость: OpenSEO. <p>\n            The open source Ahrefs alternative\n          </p>\n          <p>\n           ... (Установите API ключ в bot.py)",
        "link": "https://www.producthunt.com/products/openseo",
        "date": "2026-07-19"
    },
    {
        "title": "Acebuilder",
        "summary": "Новость: Acebuilder. <p>\n            Build landing pages with Aceternity UI\n          </p>\n          <p>\n    ... (Установите API ключ в bot.py)...",
        "content": "Новость: Acebuilder. <p>\n            Build landing pages with Aceternity UI\n          </p>\n          <p>\n    ... (Установите API ключ в bot.py)",
        "link": "https://www.producthunt.com/products/acebuilder",
        "date": "2026-07-19"
    },
    {
        "title": "ZooData",
        "summary": "Новость: ZooData. <p>\n            The data layer for AI agents\n          </p>\n          <p>\n            <a hr... (Установите API ключ в bot.py)...",
        "content": "Новость: ZooData. <p>\n            The data layer for AI agents\n          </p>\n          <p>\n            <a hr... (Установите API ключ в bot.py)",
        "link": "https://www.producthunt.com/products/zoodata",
        "date": "2026-07-18"
    },
    {
        "title": "Databricks hits $188B valuation, extending its run as AI’s favorite second act",
        "summary": "Новость: Databricks hits $188B valuation, extending its run as AI’s favorite second act. Databricks has remad... (Установите API ключ в bot.py)...",
        "content": "Новость: Databricks hits $188B valuation, extending its run as AI’s favorite second act. Databricks has remad... (Установите API ключ в bot.py)",
        "link": "https://techcrunch.com/2026/07/17/databricks-hits-188b-valuation-extending-its-run-as-ais-favorite-second-act/",
        "date": "2026-07-18"
    },
    {
        "title": "Neil Rimer thinks the AI money is coming back out",
        "summary": "Новость: Neil Rimer thinks the AI money is coming back out. Neil Rimer, the venture capitalist who co-founded... (Установите API ключ в bot.py)...",
        "content": "Новость: Neil Rimer thinks the AI money is coming back out. Neil Rimer, the venture capitalist who co-founded... (Установите API ключ в bot.py)",
        "link": "https://techcrunch.com/2026/07/17/neil-rimer-thinks-the-ai-money-is-coming-back-out/",
        "date": "2026-07-18"
    },
    {
        "title": "The Zoom hack that says, ‘Don’t record me’",
        "summary": "Новость: The Zoom hack that says, ‘Don’t record me’. If every meeting, watercooler conversation, and date get... (Установите API ключ в bot.py)...",
        "content": "Новость: The Zoom hack that says, ‘Don’t record me’. If every meeting, watercooler conversation, and date get... (Установите API ключ в bot.py)",
        "link": "https://techcrunch.com/2026/07/17/the-zoom-hack-that-says-dont-record-me/",
        "date": "2026-07-18"
    },
    {
        "title": "Patreon stops asking AI bots not to scrape — and starts blocking them",
        "summary": "Новость: Patreon stops asking AI bots not to scrape — and starts blocking them. Patreon is strengthening its ... (Установите API ключ в bot.py)...",
        "content": "Новость: Patreon stops asking AI bots not to scrape — and starts blocking them. Patreon is strengthening its ... (Установите API ключ в bot.py)",
        "link": "https://techcrunch.com/2026/07/17/patreon-stops-asking-ai-bots-not-to-scrape-and-starts-blocking-them/",
        "date": "2026-07-17"
    }
]